AsyncPayments/__init__.py
AsyncPayments/requests.py
AsyncPayments/aaio/__init__.py
AsyncPayments/aaio/api.py
AsyncPayments/aaio/models.py
AsyncPayments/cryptoBot/__init__.py
AsyncPayments/cryptoBot/api.py
AsyncPayments/cryptoBot/models.py
AsyncPayments/cryptomus/__init__.py
AsyncPayments/cryptomus/api.py
AsyncPayments/cryptomus/models.py
AsyncPayments/crystalPay/__init__.py
AsyncPayments/crystalPay/api.py
AsyncPayments/crystalPay/models.py
AsyncPayments/exceptions/__init__.py
AsyncPayments/exceptions/exceptions.py
AsyncPayments/freeKassa/__init__.py
AsyncPayments/freeKassa/api.py
AsyncPayments/freeKassa/models.py
AsyncPayments/lolz/__init__.py
AsyncPayments/lolz/api.py
AsyncPayments/lolz/models.py
AsyncPayments/payok/__init__.py
AsyncPayments/payok/api.py
AsyncPayments/payok/models.py
AsyncPayments/ruKassa/__init__.py
AsyncPayments/ruKassa/api.py
AsyncPayments/ruKassa/models.py
AsyncPayments/xrocket/__init__.py
AsyncPayments/xrocket/api.py
AsyncPayments/xrocket/models.py
asyncpayments-1.4.9.1.dist-info/licenses/LICENSE
asyncpayments-1.4.9.1.dist-info/METADATA
asyncpayments-1.4.9.1.dist-info/WHEEL
asyncpayments-1.4.9.1.dist-info/top_level.txt
asyncpayments-1.4.9.1.dist-info/RECORD
