Metadata-Version: 2.4
Name: AsyncPayments
Version: 1.4.9.1
Summary: Add payment acceptance to your projects.
Author: ToSa
Maintainer: ToSa
License: MIT License
Project-URL: Homepage, https://github.com/I-ToSa-I/AsyncPayments
Project-URL: Repository, https://github.com/I-ToSa-I/AsyncPayments
Project-URL: Issues, https://github.com/I-ToSa-I/AsyncPayments/issues
Keywords: async,payments,aaio,crypto bot,crystal pay,async payments,free kassa,ru kassa,cryptomus,xrocket,payok
Classifier: Development Status :: 5 - Production/Stable
Classifier: Natural Language :: Russian
Classifier: Natural Language :: English
Classifier: Programming Language :: Python
Classifier: Programming Language :: Python :: 3 :: Only
Classifier: Programming Language :: Python :: 3.9
Classifier: Programming Language :: Python :: 3.10
Classifier: Programming Language :: Python :: 3.11
Classifier: Topic :: Utilities
Requires-Python: >=3.9
License-File: LICENSE
Requires-Dist: aiohttp
Dynamic: license-file
